ddl2pojo/__init__.py
ddl2pojo/ddl2pojo.tpl
ddl2pojo/main.py
DdlGeneric-1.0.3.dist-info/LICENSE
DdlGeneric-1.0.3.dist-info/METADATA
DdlGeneric-1.0.3.dist-info/WHEEL
DdlGeneric-1.0.3.dist-info/entry_points.txt
DdlGeneric-1.0.3.dist-info/top_level.txt
DdlGeneric-1.0.3.dist-info/RECORD
