Metadata-Version: 2.1
Name: DdlGeneric
Version: 1.0.3
Summary: DDL文件解析程序
Home-page: https://gitee.com/visonforcoding/code-template-tools
Author: visonforcoding
Author-email: visonforcoding@gmail.com
License: UNKNOWN
Platform: UNKNOWN
Classifier: Programming Language :: Python :: 3
Classifier: License :: OSI Approved :: MIT License
Classifier: Operating System :: OS Independent
License-File: LICENSE
Requires-Dist: argparse
